nautical/__init__.py
nautical/release.py
nautical/cache/__init__.py
nautical/cache/file.py
nautical/cache/time.py
nautical/io/__init__.py
nautical/io/buoy.py
nautical/io/cdata.py
nautical/io/sources.py
nautical/io/web.py
nautical/location/__init__.py
nautical/location/point.py
nautical/location/util.py
nautical/log/__init__.py
nautical/log/log.py
nautical/noaa/__init__.py
nautical/noaa/buoy/__init__.py
nautical/noaa/buoy/buoy.py
nautical/noaa/buoy/buoy_data.py
nautical/noaa/buoy/source.py
nautical/sea_state/__init__.py
nautical/time/__init__.py
nautical/time/conversion.py
nautical/time/enums.py
nautical/time/nautical_time.py
nautical/time/ops.py
nautical/units/__init__.py
nautical/units/conversion.py
nautical/units/units.py
nautical-4.2.1.dist-info/METADATA
nautical-4.2.1.dist-info/WHEEL
nautical-4.2.1.dist-info/top_level.txt
nautical-4.2.1.dist-info/RECORD
