Metadata-Version: 2.1
Name: nautical
Version: 4.2.1
Summary: The nautical package provides users with access to historical and real time nautical information.
Home-page: https://github.com/barbacbd/nautical
Author: Brent Barbachem
Author-email: barbacbd@gmail.com
Maintainer: Brent Barbachem
Maintainer-email: barbacbd@gmail.com
License: MIT
Keywords: nautical,noaa,ocean,water
Classifier: Intended Audience :: Science/Research
Classifier: License :: Freeware
Classifier: Natural Language :: English
Classifier: Operating System :: MacOS :: MacOS X
Classifier: Operating System :: POSIX :: Linux
Classifier: Operating System :: Microsoft :: Windows
Classifier: Programming Language :: Python :: 3
Classifier: Programming Language :: Python :: 3.7
Classifier: Programming Language :: Python :: 3.8
Classifier: Programming Language :: Python :: 3.9
Classifier: Programming Language :: Python :: 3.10
Classifier: Topic :: Software Development
Requires-Python: <4,>=3.6
Requires-Dist: appdirs
Requires-Dist: bs4
Requires-Dist: pykml
Requires-Dist: pyYAML
Requires-Dist: requests
Requires-Dist: haversine
